pycellid/__init__.py
pycellid/core.py
pycellid/images.py
pycellid/io.py
pycellid-0.1.dist-info/LICENSE
pycellid-0.1.dist-info/METADATA
pycellid-0.1.dist-info/WHEEL
pycellid-0.1.dist-info/top_level.txt
pycellid-0.1.dist-info/RECORD
