Metadata-Version: 2.1
Name: pycellid
Version: 0.1
Summary: Functions to analyze single-cell
Home-page: https://github.com/pyCellID/pyCellID
Author: Clemente, José
Author-email: clemente.jac@gmail.com
License: The MIT License
Keywords: pycellid,cytometry,microscopy,cellid,vcellid
Platform: UNKNOWN
Classifier: Development Status :: 4 - Beta
Classifier: Intended Audience :: Education
Classifier: Intended Audience :: Science/Research
Classifier: Intended Audience :: Developers
Classifier: License :: OSI Approved :: MIT License
Classifier: Operating System :: OS Independent
Classifier: Programming Language :: Python :: 3.8
Classifier: Programming Language :: Python :: 3.9
Classifier: Programming Language :: Python :: Implementation :: CPython
Classifier: Topic :: Scientific/Engineering
Classifier: Topic :: Internet :: WWW/HTTP :: Dynamic Content
Classifier: Topic :: Software Development :: Libraries :: Python Modules
Requires-Python: >= 3.8
License-File: LICENSE
Requires-Dist: attrs (>=21.1.0)
Requires-Dist: pandas (>=1.3.0)
Requires-Dist: matplotlib (>=3.4.0)
Requires-Dist: numpy (>=1.21.0)
